setup.py
django_template_korean.egg-info/PKG-INFO
django_template_korean.egg-info/SOURCES.txt
django_template_korean.egg-info/dependency_links.txt
django_template_korean.egg-info/requires.txt
django_template_korean.egg-info/top_level.txt
template_korean/__init__.py
template_korean/templatetags/__init__.py
template_korean/templatetags/korean_filters.py